pytest_freezegun.py
pytest_freezegun-0.4.1.dist-info/LICENSE
pytest_freezegun-0.4.1.dist-info/METADATA
pytest_freezegun-0.4.1.dist-info/WHEEL
pytest_freezegun-0.4.1.dist-info/entry_points.txt
pytest_freezegun-0.4.1.dist-info/top_level.txt
pytest_freezegun-0.4.1.dist-info/zip-safe
pytest_freezegun-0.4.1.dist-info/RECORD
