Metadata-Version: 2.1
Name: pytest-freezegun
Version: 0.4.1
Summary: Wrap tests with fixtures in freeze_time
Home-page: https://github.com/ktosiek/pytest-freezegun
Author: Tomasz Kontusz
Author-email: tomasz.kontusz@gmail.com
Maintainer: Tomasz Kontusz
Maintainer-email: tomasz.kontusz@gmail.com
License: MIT
Platform: UNKNOWN
Classifier: Development Status :: 4 - Beta
Classifier: Framework :: Pytest
Classifier: Intended Audience :: Developers
Classifier: Topic :: Software Development :: Testing
Classifier: Programming Language :: Python
Classifier: Programming Language :: Python :: 3
Classifier: Programming Language :: Python :: 3.5
Classifier: Programming Language :: Python :: 3.6
Classifier: Programming Language :: Python :: 3.7
Classifier: Programming Language :: Python :: 3.8
Classifier: Programming Language :: Python :: Implementation :: CPython
Classifier: Programming Language :: Python :: Implementation :: PyPy
Classifier: Operating System :: OS Independent
Classifier: License :: OSI Approved :: MIT License
Requires-Dist: freezegun (>0.3)
Requires-Dist: pytest (>=3.0.0)
